smbclientng/__init__.py
smbclientng/__main__.py
smbclientng/core/CommandCompleter.py
smbclientng/core/Config.py
smbclientng/core/Credentials.py
smbclientng/core/InteractiveShell.py
smbclientng/core/LocalFileIO.py
smbclientng/core/Logger.py
smbclientng/core/Module.py
smbclientng/core/ModuleArgumentParser.py
smbclientng/core/SIDResolver.py
smbclientng/core/SMBSession.py
smbclientng/core/SessionsManager.py
smbclientng/core/__init__.py
smbclientng/core/utils.py
smbclientng/modules/Extract.py
smbclientng/modules/Find.py
smbclientng/modules/GPPPasswords.py
smbclientng/modules/Users.py
smbclientng/modules/__init__.py
smbclientng-2.1.7.dist-info/LICENSE
smbclientng-2.1.7.dist-info/METADATA
smbclientng-2.1.7.dist-info/WHEEL
smbclientng-2.1.7.dist-info/entry_points.txt
smbclientng-2.1.7.dist-info/top_level.txt
smbclientng-2.1.7.dist-info/RECORD
