Metadata-Version: 2.1
Name: smbclientng
Version: 2.1.7
Summary: smbclient-ng, a fast and user friendly way to interact with SMB shares.
Home-page: https://github.com/p0dalirius/smbclient-ng
Author: Podalirius
Author-email: podalirius@protonmail.com
License: GPL3
Classifier: Programming Language :: Python :: 3
Classifier: License :: OSI Approved :: GNU General Public License v3 (GPLv3)
Classifier: Operating System :: OS Independent
Requires-Python: >=3.6
License-File: LICENSE
Requires-Dist: charset-normalizer
Requires-Dist: impacket
Requires-Dist: pefile
Requires-Dist: rich
